README.txt
setup.py
bin/bgg_query
bin/top_rated
libBGG/BGGAPI.py
libBGG/BGGCache.py
libBGG/Boardgame.py
libBGG/Collection.py
libBGG/Guild.py
libBGG/User.py
libBGG/__init__.py
libBGG.egg-info/PKG-INFO
libBGG.egg-info/SOURCES.txt
libBGG.egg-info/dependency_links.txt
libBGG.egg-info/top_level.txt