Metadata-Version: 1.0
Name: libBGG
Version: 0.1.5
Summary: A python interface to the boardgamegeek.com API and boardgame utils.
Home-page: https://github.com/philsstein/libBGG
Author: Geoff Lawler
Author-email: geoff.lawler@gmail.com
License: FreeBSD License
Platform: UNKNOWN
